argclz/__init__.py
argclz/_types.py
argclz/_validator.py
argclz/clone.py
argclz/commands.py
argclz/core.py
argclz/types.py
argclz/validator.py
argclz/dispatch/__init__.py
argclz/dispatch/annotations.py
argclz/dispatch/builder.py
argclz/dispatch/core.py
argclz-1.0.1.dist-info/licenses/LICENSE
argclz-1.0.1.dist-info/METADATA
argclz-1.0.1.dist-info/WHEEL
argclz-1.0.1.dist-info/top_level.txt
argclz-1.0.1.dist-info/RECORD
