Metadata-Version: 2.4
Name: argclz
Version: 1.0.1
Summary: Create commandline interface via dataclass-like class
Author-email: Yu-Ting Wei <ytsimon2004@gmail.com>, Ta-Shun Su <antoniost29@gmail.com>
License: BSD 3-Clause License
Project-URL: Homepage, https://github.com/ytsimon2004/argclz
Project-URL: Documentation, https://argclz.readthedocs.io/en/latest/
Project-URL: Repository, https://github.com/ytsimon2004/argclz
Project-URL: Issues, https://github.com/ytsimon2004/argclz/issues
Keywords: commandline
Classifier: Development Status :: 3 - Alpha
Classifier: Programming Language :: Python :: 3.10
Classifier: Programming Language :: Python :: 3.11
Classifier: Programming Language :: Python :: 3.12
Classifier: License :: OSI Approved :: BSD License
Classifier: Natural Language :: English
Classifier: Operating System :: OS Independent
Classifier: Topic :: Utilities
Classifier: Intended Audience :: Developers
Classifier: Typing :: Typed
Requires-Python: >=3.10
License-File: LICENSE
Requires-Dist: typing_extensions
Provides-Extra: dev
Requires-Dist: pytest; extra == "dev"
Requires-Dist: pytest-cov; extra == "dev"
Provides-Extra: doc
Requires-Dist: sphinx; extra == "doc"
Requires-Dist: pydata-sphinx-theme; extra == "doc"
Requires-Dist: sphinx_prompt; extra == "doc"
Requires-Dist: sphinx_copybutton; extra == "doc"
Dynamic: license-file
